trajtracker/_Environment.py
trajtracker/_TTrkObject.py
trajtracker/__init__.py
trajtracker/_debug.py
trajtracker/_ttrk_funcs.py
trajtracker/_utils.py
trajtracker/utils.py
trajtracker/events/_Event.py
trajtracker/events/_EventManager.py
trajtracker/events/_OnsetOffsetObj.py
trajtracker/events/__init__.py
trajtracker/io/_CSVLoader.py
trajtracker/io/_Mouse.py
trajtracker/io/__init__.py
trajtracker/io/csv_formats.py
trajtracker/misc/_EnabledDisabledObj.py
trajtracker/misc/_LocationColorMap.py
trajtracker/misc/__init__.py
trajtracker/misc/nvshapes/_Circle.py
trajtracker/misc/nvshapes/_Rectangle.py
trajtracker/misc/nvshapes/_Sector.py
trajtracker/misc/nvshapes/__init__.py
trajtracker/movement/_CircularTrajectoryGenerator.py
trajtracker/movement/_CustomTrajectoryGenerator.py
trajtracker/movement/_DirectionMonitor.py
trajtracker/movement/_Hotspot.py
trajtracker/movement/_LineTrajectoryGenerator.py
trajtracker/movement/_RectStartPoint.py
trajtracker/movement/_SegmentedTrajectoryGenerator.py
trajtracker/movement/_SpeedMonitor.py
trajtracker/movement/_StartPoint.py
trajtracker/movement/_StimulusAnimator.py
trajtracker/movement/_TrajectoryTracker.py
trajtracker/movement/__init__.py
trajtracker/stimuli/_BaseMultiStim.py
trajtracker/stimuli/_FixationZoom.py
trajtracker/stimuli/_MultiStimulus.py
trajtracker/stimuli/_MultiTextBox.py
trajtracker/stimuli/_NumberLine.py
trajtracker/stimuli/_Slider.py
trajtracker/stimuli/_StimulusContainer.py
trajtracker/stimuli/_StimulusSelector.py
trajtracker/stimuli/__init__.py
trajtracker/validators/_ExperimentError.py
trajtracker/validators/_FingerLiftedValidator.py
trajtracker/validators/_GlobalSpeedValidator.py
trajtracker/validators/_InstantaneousSpeedValidator.py
trajtracker/validators/_LocationsValidator.py
trajtracker/validators/_MoveByGradientValidator.py
trajtracker/validators/_MovementAngleValidator.py
trajtracker/validators/_NCurvesValidator.py
trajtracker/validators/__init__.py
trajtracker-1.2.1.dist-info/LICENSE.txt
trajtracker-1.2.1.dist-info/METADATA
trajtracker-1.2.1.dist-info/WHEEL
trajtracker-1.2.1.dist-info/top_level.txt
trajtracker-1.2.1.dist-info/RECORD
