Metadata-Version: 2.1
Name: trajtracker
Version: 1.2.1
Summary: Framework for creating trajectory-tracking experiments
Home-page: http://trajtracker.com
Author: Dror Dotan
Author-email: dror@trajtracker.com
License: GPL
Platform: UNKNOWN
Classifier: Development Status :: 4 - Beta
Classifier: Intended Audience :: Science/Research
Classifier: Topic :: Scientific/Engineering
Classifier: Programming Language :: Python :: 2.7
Classifier: Programming Language :: Python :: 3.6
Requires-Dist: expyriment
Requires-Dist: numpy
Requires-Dist: enum34
Requires-Dist: pandas
Requires-Dist: pygame
